jupyterlab_cell_status_extension/__init__.py
jupyterlab_cell_status_extension/_version.py
jupyterlab_cell_status_extension-0.2.2.data/data/share/jupyter/labextensions/jupyterlab_cell_status_extension/build_log.json
jupyterlab_cell_status_extension-0.2.2.data/data/share/jupyter/labextensions/jupyterlab_cell_status_extension/package.json
jupyterlab_cell_status_extension-0.2.2.data/data/share/jupyter/labextensions/jupyterlab_cell_status_extension/schemas/jupyterlab_cell_status_extension/package.json.orig
jupyterlab_cell_status_extension-0.2.2.data/data/share/jupyter/labextensions/jupyterlab_cell_status_extension/schemas/jupyterlab_cell_status_extension/plugin.json
jupyterlab_cell_status_extension-0.2.2.data/data/share/jupyter/labextensions/jupyterlab_cell_status_extension/static/lib_index_js.f01c756a6629cc3591eb.js
jupyterlab_cell_status_extension-0.2.2.data/data/share/jupyter/labextensions/jupyterlab_cell_status_extension/static/lib_index_js.f01c756a6629cc3591eb.js.map
jupyterlab_cell_status_extension-0.2.2.data/data/share/jupyter/labextensions/jupyterlab_cell_status_extension/static/remoteEntry.dea3be653aac68287c73.js
jupyterlab_cell_status_extension-0.2.2.data/data/share/jupyter/labextensions/jupyterlab_cell_status_extension/static/remoteEntry.dea3be653aac68287c73.js.map
jupyterlab_cell_status_extension-0.2.2.data/data/share/jupyter/labextensions/jupyterlab_cell_status_extension/static/style.js
jupyterlab_cell_status_extension-0.2.2.data/data/share/jupyter/labextensions/jupyterlab_cell_status_extension/static/style_index_js.58845088dcdbe3db9488.js
jupyterlab_cell_status_extension-0.2.2.data/data/share/jupyter/labextensions/jupyterlab_cell_status_extension/static/style_index_js.58845088dcdbe3db9488.js.map
jupyterlab_cell_status_extension-0.2.2.data/data/share/jupyter/labextensions/jupyterlab_cell_status_extension/install.json
jupyterlab_cell_status_extension-0.2.2.dist-info/METADATA
jupyterlab_cell_status_extension-0.2.2.dist-info/WHEEL
jupyterlab_cell_status_extension-0.2.2.dist-info/licenses/LICENSE
jupyterlab_cell_status_extension-0.2.2.dist-info/RECORD
